README.txt
setup.cfg
setup.py
headspin_cli/__init__.py
headspin_cli/api.py
headspin_cli/cli.py
headspin_cli/config.py
headspin_cli/connect_method.py
headspin_cli/version.py
headspin_cli.egg-info/PKG-INFO
headspin_cli.egg-info/SOURCES.txt
headspin_cli.egg-info/dependency_links.txt
headspin_cli.egg-info/entry_points.txt
headspin_cli.egg-info/requires.txt
headspin_cli.egg-info/top_level.txt