Metadata-Version: 1.1
Name: headspin-cli
Version: 0.4.3
Summary: HeadSpin platform command-line interface
Home-page: https://github.com/projectxyzio/headspin-cli
Author: HeadSpin
Author-email: marius@headspin.io
License: UNKNOWN
Download-URL: https://github.com/projectxyzio/headspin-cli
Keywords: testing,mobile,API,console,docker
Platform: UNKNOWN
Classifier: License :: OSI Approved :: MIT License
Classifier: Development Status :: 5 - Production/Stable
Classifier: Environment :: Console
Classifier: Operating System :: MacOS :: MacOS X
Classifier: Operating System :: POSIX
Classifier: Programming Language :: Python
Classifier: Programming Language :: Python :: 2
Classifier: Programming Language :: Python :: 2.7
Classifier: Programming Language :: Python :: Implementation :: CPython
Classifier: Topic :: Internet
Classifier: Topic :: Internet :: WWW/HTTP
Classifier: Topic :: Internet :: Proxy Servers
Classifier: Topic :: Software Development :: Testing
